{
  "year": 2025,
  "entries": [
    {
      "id": "film-20251228",
      "date": "2025-12-28",
      "title": "Wonka",
      "year": 2023,
      "rating": 3,
      "platform": "Max",
      "runtime": 116,
      "genre": [
        "Musical",
        "Fantasy"
      ]
    },
    {
      "id": "film-20251220",
      "date": "2025-12-20",
      "title": "Oppenheimer",
      "year": 2023,
      "rating": 5,
      "platform": "Prime Video",
      "runtime": 180,
      "genre": [
        "Drama",
        "History"
      ],
      "notes": "Absolutely stunning. Nolan's best work."
    },
    {
      "id": "film-20251215",
      "date": "2025-12-15",
      "title": "Barbie",
      "year": 2023,
      "rating": 4,
      "platform": "Max",
      "runtime": 114,
      "genre": [
        "Comedy",
        "Fantasy"
      ]
    },
    {
      "id": "film-20251201",
      "date": "2025-12-01",
      "title": "Killers of the Flower Moon",
      "year": 2023,
      "rating": 4,
      "platform": "Apple TV+",
      "runtime": 206,
      "genre": [
        "Crime",
        "Drama",
        "History"
      ]
    }
  ]
}
